Metadata-Version: 2.1
Name: simplesam
Version: 0.1.4.1
Summary: Simple pure Python SAM parser and objects for working with SAM records
Home-page: http://mattshirley.com
Author: Matthew Shirley
Author-email: mdshw5@gmail.com
License: MIT
Platform: UNKNOWN
Classifier: Development Status :: 5 - Production/Stable
Classifier: License :: OSI Approved :: MIT License
Classifier: Environment :: Console
Classifier: Intended Audience :: Science/Research
Classifier: Natural Language :: English
Classifier: Operating System :: Unix
Classifier: Programming Language :: Python :: 2.7
Classifier: Programming Language :: Python :: 3.10
Classifier: Topic :: Scientific/Engineering :: Bio-Informatics
License-File: LICENSE
